sciencemaker/__init__.py
sciencemaker-0.0.0.dist-info/LICENCE.txt
sciencemaker-0.0.0.dist-info/METADATA
sciencemaker-0.0.0.dist-info/WHEEL
sciencemaker-0.0.0.dist-info/top_level.txt
sciencemaker-0.0.0.dist-info/RECORD
