Metadata-Version: 2.1
Name: sciencemaker
Version: 0.0.0
Summary: This package is open for student, any student and teacher can use this.
Home-page: UNKNOWN
Author: Dipkumar
Author-email: iot.nbu@gmail.com
License: UNKNOWN
Keywords: sciencemaker
Platform: UNKNOWN
Classifier: Programming Language :: Python :: 3.10
Classifier: Operating System :: OS Independent
License-File: LICENCE.txt
